Workbook

Sheet Anleitung
A1: eBay Preiskalkulation und Upload-Vorlage
A2: Stand der Gebühren: 19.10.2026. Quelle gewerblich: https://www.ebay.de/help/selling/fees-credits-invoices/gebhren-fr-gewerbliche-verkufer?id=4809
A3: Quelle privat: https://www.ebay.de/help/selling/fees-credits-invoices/selling-fees?id=4822
A5: So benutzst du die Datei
A6: 1. Blatt 'Kalkulation': oben die Einstellungen (gelbe Felder) auf dein Konto anpassen.
A7: 2. Pro Artikel eine Zeile ausfüllen. Nur blaue Zahlen eintragen, alles Schwarze rechnet sich selbst.
A8: 3. Kategorie-Gruppe aus der Auswahlliste wählen. Die Provision kommt automatisch aus dem Blatt 'Gebühren'.
A9: 4. Spalte 'Zielpreis bei Wunschmarge' sagt dir, was der Artikel mindestens kosten muss, damit deine Wunschmarge bleibt.
A10: 5. Blatt 'Upload-Vorlage': fertige Angebote eintragen, dann als CSV (UTF-8) speichern und im Verkäufer-Cockpit unter Berichte > Hochladen einspielen.
A12: Farblegende
A13: Blau = Eingabe (deine Zahlen). Schwarz = Formel, nicht überschreiben. Grün = Verweis auf anderes Blatt. Gelb hinterlegt = Einstellung, die du prüfen musst.
A15: Annahmen, die in den Formeln stecken
... A27: Wer regelmäßig Neuware mit Gewinnabsicht verkauft, handelt gewerblich: Gewerbeanmeldung, Impressum, Widerrufsbelehrung, LUCID-Registrierung, GPSR-Herstellerangaben. Die Tabelle ersetzt keine Steuerberatung.

Sheet Kalkulation
A1: eBay Preiskalkulation je Artikel
A3: Einstellungen
A4: Kontotyp | B4: Gewerblich | C4: Privat oder Gewerblich. Privat = 0 % Provision, aber nur für echte Gelegenheitsverkäufe erlaubt.
A5: USt-Satz auf Verkäufe | B5: 0.19 | C5: 19 % Regelbesteuerung. 0 % bei Kleinunternehmer (§ 19 UStG) oder Privat.
A6: Vorsteuerabzug auf eBay-Gebühren | B6: Ja | C6: Ja = USt auf eBay-Gebühren holst du dir zurück. Nein bei Privat/Kleinunternehmer.
A7: Wunschmarge (vom Gesamtbetrag) | B7: 0.2 | C7: Zielgewinn nach allen Kosten, Steuern und Gebühren.
A8: Promoted Listings (Anzeigen) Standard | B8: 0 | C8: Anzeigenrate, falls du Angebote bewirbst. 0 % wenn nicht.
A9: Erwartete Verkäufe je Angebot und Monat | B9: 1 | C9: Verteilt die monatliche Angebotsgebühr auf die Verkäufe.
A11: Blau eintragen, Schwarz rechnet. Eine Zeile je Artikel.
A12: Nr. | B12: Artikel / SKU | C12: Kategorie-Gruppe (Auswahl) | D12: Einkaufspreis (€) | E12: Anteil Einkaufs-Versand (€) | F12: Verpackung (€) | G12: Mein Versand zum Kunden (€) | H12: Versand, den Käufer zahlt (€) | I12: Verkaufspreis Artikel (€) | J12: Anzeigen-Rate (%) | K12: Retourenquote (%) | L12: Gesamtbetrag Käufer (€) | M12: Provision (%) | N12: Provision (€) | O12: Fixanteil (€) | P12: Angebotsgebühr je Verkauf (€) | Q12: Anzeigen (€) | R12: eBay-Gebühren netto (€) | S12: USt auf Gebühren, nicht abziehbar (€) | T12: USt auf Verkauf ans Finanzamt (€) | U12: Ware + Verpackung + Versand (€) | V12: Retourenrisiko (€) | W12: Gewinn je Verkauf (€) | X12: Marge (% vom Gesamtbetrag) | Y12: Gewinn in % vom Einkauf | Z12: Break-even Verkaufspreis (€) | AA12: Zielpreis bei Wunschmarge (€) | AB12: Preis-Check
A13: 1 | B13: LED-Streifen 5 m mit Fernbedienung | C13: Technik: Zubehör (Kabel, Handy-Zubehör, Hüllen, Tastaturen, Ladegeräte) | D13: 6.9 | E13: 0.6 | F13: 0.4 | G13: 3.99 | H13: 0 | I13: 19.99 | J13: 0 | K13: 0.05 | L13: =IF(I13="","",I13+H13) -> 19.99 | M13: =IF(I13="","",IF($B$4="Privat",0,IFERROR(INDEX(Gebühren!$B$2:$B$18,MATCH(C13,Gebühren!$A$2:$A$18,0)),0.14))) -> 0.12 | N13: =IF(I13="","",IF($B$4="Privat",0,IF(OR(IFERROR(INDEX(Gebühren!$C$2:$C$18,MATCH(C13,Gebühren!$A$2:$A$18,0)),0)=0,L13<=IFERROR(INDEX(Gebühren!$C$2:$C$18,MATCH(C13,Gebühren!$A$2:$A$18,0)),0)),L13*M13,INDEX(Gebühren!$C$2:$C$18,MATCH(C13,Gebühren!$A$2:$A$18,0))*M13+(L13-INDEX(Gebühren!$C$2:$C$18,MATCH(C13,Gebühren!$A$2:$A$18,0)))*IFERROR(INDEX(Gebühren!$D$2:$D$18,MATCH(C13,Gebühren!$A$2:$A$18,0)),0.03)))) -> 2.3988 | O13: =IF(I13="","",IF($B$4="Privat",0,IF(L13<=10,Gebühren!$B$21,Gebühren!$B$22))) -> 0.45 | P13: =IF(I13="","",IF($B$4="Privat",0,Gebühren!$B$23/MAX(1,$B$9))) -> 0.35 | Q13: =IF(I13="","",L13*IF(J13="",$B$8,J13)) -> 0 | R13: =IF(I13="","",N13+O13+P13+Q13) -> 3.1988 | S13: =IF(I13="","",IF($B$6="Ja",0,R13*0.19)) -> 0 | T13: =IF(I13="","",L13-L13/(1+$B$5)) -> 3.1916807 | U13: =IF(I13="","",D13+E13+F13+G13) -> 11.89 | V13: =IF(I13="","",U13*K13) -> 0.5945 | W13: =IF(I13="","",L13-R13-S13-T13-U13-V13) -> 1.1150193 | X13: =IF(I13="","",IF(L13=0,0,W13/L13)) -> 0.055778856 | Y13: =IF(I13="","",IF(D13=0,0,W13/D13)) -> 0.161597 | Z13: =IF(I13="","",IF(1-((M13+IF(J13="",$B$8,J13))*(1+IF($B$6="Ja",0,0.19))+$B$5/(1+$B$5))<=0,"n/a",((O13+P13)*(1+IF($B$6="Ja",0,0.19))+U13+V13)/(1-((M13+IF(J13="",$B$8,J13))*(1+IF($B$6="Ja",0,0.19))+$B$5/(1+$B$5)))-H13)) -> 18.442085 | AA13: =IF(I13="","",IF(1-((M13+IF(J13="",$B$8,J13))*(1+IF($B$6="Ja",0,0.19))+$B$5/(1+$B$5))-$B$7<=0,"n/a",((O13+P13)*(1+IF($B$6="Ja",0,0.19))+U13+V13)/(1-((M13+IF(J13="",$B$8,J13))*(1+IF($B$6="Ja",0,0.19))+$B$5/(1+$B$5))-$B$7)-H13)) -> 25.530612 | AB13: =IF(I13="","",IF(W13<0,"Verlust",IF(X13<$B$7,"unter Wunschmarge","ok"))) -> unter Wunschmarge
A14: 2 | B14: Handyhülle Silikon iPhone | C14: Technik: Zubehör (Kabel, Handy-Zubehör, Hüllen, Tastaturen, Ladegeräte) | D14: 1.8 | E14: 0.3 | F14: 0.2 | G14: 1.8 | H14: 0 | I14: 9.99 | J14: 0 | K14: 0.03 | L14: =IF(I14="","",I14+H14) -> 9.99 | M14: =IF(I14="","",IF($B$4="Privat",0,IFERROR(INDEX(Gebühren!$B$2:$B$18,MATCH(C14,Gebühren!$A$2:$A$18,0)),0.14))) -> 0.12 | N14: =IF(I14="","",IF($B$4="Privat",0,IF(OR(IFERROR(INDEX(Gebühren!$C$2:$C$18,MATCH(C14,Gebühren!$A$2:$A$18,0)),0)=0,L14<=IFERROR(INDEX(Gebühren!$C$2:$C$18,MATCH(C14,Gebühren!$A$2:$A$18,0)),0)),L14*M14,INDEX(Gebühren!$C$2:$C$18,MATCH(C14,Gebühren!$A$2:$A$18,0))*M14+(L14-INDEX(Gebühren!$C$2:$C$18,MATCH(C14,Gebühren!$A$2:$A$18,0)))*IFERROR(INDEX(Gebühren!$D$2:$D$18,MATCH(C14,Gebühren!$A$2:$A$18,0)),0.03)))) -> 1.1988 | O14: =IF(I14="","",IF($B$4="Privat",0,IF(L14<=10,Gebühren!$B$21,Gebühren!$B$22))) -> 0.35 | P14: =IF(I14="","",IF($B$4="Privat",0,Gebühren!$B$23/MAX(1,$B$9))) -> 0.35 | Q14: =IF(I14="","",L14*IF(J14="",$B$8,J14)) -> 0 | R14: =IF(I14="","",N14+O14+P14+Q14) -> 1.8988 | S14: =IF(I14="","",IF($B$6="Ja",0,R14*0.19)) -> 0 | T14: =IF(I14="","",L14-L14/(1+$B$5)) -> 1.595042 | U14: =IF(I14="","",D14+E14+F14+G14) -> 4.1 | V14: =IF(I14="","",U14*K14) -> 0.123 | W14: =IF(I14="","",L14-R14-S14-T14-U14-V14) -> 2.273158 | X14: =IF(I14="","",IF(L14=0,0,W14/L14)) -> 0.22754334 | Y14: =IF(I14="","",IF(D14=0,0,W14/D14)) -> 1.2628655 | Z14: =IF(I14="","",IF(1-((M14+IF(J14="",$B$8,J14))*(1+IF($B$6="Ja",0,0.19))+$B$5/(1+$B$5))<=0,"n/a",((O14+P14)*(1+IF($B$6="Ja",0,0.19))+U14+V14)/(1-((M14+IF(J14="",$B$8,J14))*(1+IF($B$6="Ja",0,0.19))+$B$5/(1+$B$5)))-H14)) -> 6.8343094 | AA14: =IF(I14="","",IF(1-((M14+IF(J14="",$B$8,J14))*(1+IF($B$6="Ja",0,0.19))+$B$5/(1+$B$5))-$B$7<=0,"n/a",((O14+P14)*(1+IF($B$6="Ja",0,0.19))+U14+V14)/(1-((M14+IF(J14="",$B$8,J14))*(1+IF($B$6="Ja",0,0.19))+$B$5/(1+$B$5))-$B$7)-H14)) -> 9.4611919 | AB14: =IF(I14="","",IF(W14<0,"Verlust",IF(X14<$B$7,"unter Wunschmarge","ok"))) -> ok
A15: 3 | B15: Küchen-Organizer 3er-Set | C15: Möbel & Wohnen (Deko, Küche, Organizer, Haushalt ohne Elektrogeräte) | D15: 7.5 | E15: 0.8 | F15: 0.5 | G15: 4.99 | H15: 4.99 | I15: 24.99 | J15: 0 | K15: 0.05 | L15: =IF(I15="","",I15+H15) -> 29.98 | M15: =IF(I15="","",IF($B$4="Privat",0,IFERROR(INDEX(Gebühren!$B$2:$B$18,MATCH(C15,Gebühren!$A$2:$A$18,0)),0.14))) -> 0.14 | N15: =IF(I15="","",IF($B$4="Privat",0,IF(OR(IFERROR(INDEX(Gebühren!$C$2:$C$18,MATCH(C15,Gebühren!$A$2:$A$18,0)),0)=0,L15<=IFERROR(INDEX(Gebühren!$C$2:$C$18,MATCH(C15,Gebühren!$A$2:$A$18,0)),0)),L15*M15,INDEX(Gebühren!$C$2:$C$18,MATCH(C15,Gebühren!$A$2:$A$18,0))*M15+(L15-INDEX(Gebühren!$C$2:$C$18,MATCH(C15,Gebühren!$A$2:$A$18,0)))*IFERROR(INDEX(Gebühren!$D$2:$D$18,MATCH(C15,Gebühren!$A$2:$A$18,0)),0.03)))) -> 4.1972 | O15: =IF(I15="","",IF($B$4="Privat",0,IF(L15<=10,Gebühren!$B$21,Gebühren!$B$22))) -> 0.45 | P15: =IF(I15="","",IF($B$4="Privat",0,Gebühren!$B$23/MAX(1,$B$9))) -> 0.35 | Q15: =IF(I15="","",L15*IF(J15="",$B$8,J15)) -> 0 | R15: =IF(I15="","",N15+O15+P15+Q15) -> 4.9972 | S15: =IF(I15="","",IF($B$6="Ja",0,R15*0.19)) -> 0 | T15: =IF(I15="","",L15-L15/(1+$B$5)) -> 4.7867227 | U15: =IF(I15="","",D15+E15+F15+G15) -> 13.79 | V15: =IF(I15="","",U15*K15) -> 0.6895 | W15: =IF(I15="","",L15-R15-S15-T15-U15-V15) -> 5.7165773 | X15: =IF(I15="","",IF(L15=0,0,W15/L15)) -> 0.1906797 | Y15: =IF(I15="","",IF(D15=0,0,W15/D15)) -> 0.76221031 | Z15: =IF(I15="","",IF(1-((M15+IF(J15="",$B$8,J15))*(1+IF($B$6="Ja",0,0.19))+$B$5/(1+$B$5))<=0,"n/a",((O15+P15)*(1+IF($B$6="Ja",0,0.19))+U15+V15)/(1-((M15+IF(J15="",$B$8,J15))*(1+IF($B$6="Ja",0,0.19))+$B$5/(1+$B$5)))-H15)) -> 16.827381 | AA15: =IF(I15="","",IF(1-((M15+IF(J15="",$B$8,J15))*(1+IF($B$6="Ja",0,0.19))+$B$5/(1+$B$5))-$B$7<=0,"n/a",((O15+P15)*(1+IF($B$6="Ja",0,0.19))+U15+V15)/(1-((M15+IF(J15="",$B$8,J15))*(1+IF($B$6="Ja",0,0.19))+$B$5/(1+$B$5))-$B$7)-H15)) -> 25.54847 | AB15: =IF(I15="","",IF(W15<0,"Verlust",IF(X15<$B$7,"unter Wunschmarge","ok"))) -> unter Wunschmarge
A16: 4 | L16: =IF(I16="","",I16+H16) | M16: =IF(I16="","",IF($B$4="Privat",0,IFERROR(INDEX(Gebühren!$B$2:$B$18,MATCH(C16,Gebühren!$A$2:$A$18,0)),0.14))) | N16: =IF(I16="","",IF($B$4="Privat",0,IF(OR(IFERROR(INDEX(Gebühren!$C$2:$C$18,MATCH(C16,Gebühren!$A$2:$A$18,0)),0)=0,L16<=IFERROR(INDEX(Gebühren!$C$2:$C$18,MATCH(C16,Gebühren!$A$2:$A$18,0)),0)),L16*M16,INDEX(Gebühren!$C$2:$C$18,MATCH(C16,Gebühren!$A$2:$A$18,0))*M16+(L16-INDEX(Gebühren!$C$2:$C$18,MATCH(C16,Gebühren!$A$2:$A$18,0)))*IFERROR(INDEX(Gebühren!$D$2:$D$18,MATCH(C16,Gebühren!$A$2:$A$18,0)),0.03)))) | O16: =IF(I16="","",IF($B$4="Privat",0,IF(L16<=10,Gebühren!$B$21,Gebühren!$B$22))) | P16: =IF(I16="","",IF($B$4="Privat",0,Gebühren!$B$23/MAX(1,$B$9))) | Q16: =IF(I16="","",L16*IF(J16="",$B$8,J16)) | R16: =IF(I16="","",N16+O16+P16+Q16) | S16: =IF(I16="","",IF($B$6="Ja",0,R16*0.19)) | T16: =IF(I16="","",L16-L16/(1+$B$5)) | U16: =IF(I16="","",D16+E16+F16+G16) | V16: =IF(I16="","",U16*K16) | W16: =IF(I16="","",L16-R16-S16-T16-U16-V16) | X16: =IF(I16="","",IF(L16=0,0,W16/L16)) | Y16: =IF(I16="","",IF(D16=0,0,W16/D16)) | Z16: =IF(I16="","",IF(1-((M16+IF(J16="",$B$8,J16))*(1+IF($B$6="Ja",0,0.19))+$B$5/(1+$B$5))<=0,"n/a",((O16+P16)*(1+IF($B$6="Ja",0,0.19))+U16+V16)/(1-((M16+IF(J16="",$B$8,J16))*(1+IF($B$6="Ja",0,0.19))+$B$5/(1+$B$5)))-H16)) | AA16: =IF(I16="","",IF(1-((M16+IF(J16="",$B$8,J16))*(1+IF($B$6="Ja",0,0.19))+$B$5/(1+$B$5))-$B$7<=0,"n/a",((O16+P16)*(1+IF($B$6="Ja",0,0.19))+U16+V16)/(1-((M16+IF(J16="",$B$8,J16))*(1+IF($B$6="Ja",0,0.19))+$B$5/(1+$B$5))-$B$7)-H16)) | AB16: =IF(I16="","",IF(W16<0,"Verlust",IF(X16<$B$7,"unter Wunschmarge","ok")))
A17: 5 | L17: =IF(I17="","",I17+H17) | M17: =IF(I17="","",IF($B$4="Privat",0,IFERROR(INDEX(Gebühren!$B$2:$B$18,MATCH(C17,Gebühren!$A$2:$A$18,0)),0.14))) | N17: =IF(I17="","",IF($B$4="Privat",0,IF(OR(IFERROR(INDEX(Gebühren!$C$2:$C$18,MATCH(C17,Gebühren!$A$2:$A$18,0)),0)=0,L17<=IFERROR(INDEX(Gebühren!$C$2:$C$18,MATCH(C17,Gebühren!$A$2:$A$18,0)),0)),L17*M17,INDEX(Gebühren!$C$2:$C$18,MATCH(C17,Gebühren!$A$2:$A$18,0))*M17+(L17-INDEX(Gebühren!$C$2:$C$18,MATCH(C17,Gebühren!$A$2:$A$18,0)))*IFERROR(INDEX(Gebühren!$D$2:$D$18,MATCH(C17,Gebühren!$A$2:$A$18,0)),0.03)))) | O17: =IF(I17="","",IF($B$4="Privat",0,IF(L17<=10,Gebühren!$B$21,Gebühren!$B$22))) | P17: =IF(I17="","",IF($B$4="Privat",0,Gebühren!$B$23/MAX(1,$B$9))) | Q17: =IF(I17="","",L17*IF(J17="",$B$8,J17)) | R17: =IF(I17="","",N17+O17+P17+Q17) | S17: =IF(I17="","",IF($B$6="Ja",0,R17*0.19)) | T17: =IF(I17="","",L17-L17/(1+$B$5)) | U17: =IF(I17="","",D17+E17+F17+G17) | V17: =IF(I17="","",U17*K17) | W17: =IF(I17="","",L17-R17-S17-T17-U17-V17) | X17: =IF(I17="","",IF(L17=0,0,W17/L17)) | Y17: =IF(I17="","",IF(D17=0,0,W17/D17)) | Z17: =IF(I17="","",IF(1-((M17+IF(J17="",$B$8,J17))*(1+IF($B$6="Ja",0,0.19))+$B$5/(1+$B$5))<=0,"n/a",((O17+P17)*(1+IF($B$6="Ja",0,0.19))+U17+V17)/(1-((M17+IF(J17="",$B$8,J17))*(1+IF($B$6="Ja",0,0.19))+$B$5/(1+$B$5)))-H17)) | AA17: =IF(I17="","",IF(1-((M17+IF(J17="",$B$8,J17))*(1+IF($B$6="Ja",0,0.19))+$B$5/(1+$B$5))-$B$7<=0,"n/a",((O17+P17)*(1+IF($B$6="Ja",0,0.19))+U17+V17)/(1-((M17+IF(J17="",$B$8,J17))*(1+IF($B$6="Ja",0,0.19))+$B$5/(1+$B$5))-$B$7)-H17)) | AB17: =IF(I17="","",IF(W17<0,"Verlust",IF(X17<$B$7,"unter Wunschmarge","ok")))
A18: 6 | L18: =IF(I18="","",I18+H18) | M18: =IF(I18="","",IF($B$4="Privat",0,IFERROR(INDEX(Gebühren!$B$2:$B$18,MATCH(C18,Gebühren!$A$2:$A$18,0)),0.14))) | N18: =IF(I18="","",IF($B$4="Privat",0,IF(OR(IFERROR(INDEX(Gebühren!$C$2:$C$18,MATCH(C18,Gebühren!$A$2:$A$18,0)),0)=0,L18<=IFERROR(INDEX(Gebühren!$C$2:$C$18,MATCH(C18,Gebühren!$A$2:$A$18,0)),0)),L18*M18,INDEX(Gebühren!$C$2:$C$18,MATCH(C18,Gebühren!$A$2:$A$18,0))*M18+(L18-INDEX(Gebühren!$C$2:$C$18,MATCH(C18,Gebühren!$A$2:$A$18,0)))*IFERROR(INDEX(Gebühren!$D$2:$D$18,MATCH(C18,Gebühren!$A$2:$A$18,0)),0.03)))) | O18: =IF(I18="","",IF($B$4="Privat",0,IF(L18<=10,Gebühren!$B$21,Gebühren!$B$22))) | P18: =IF(I18="","",IF($B$4="Privat",0,Gebühren!$B$23/MAX(1,$B$9))) | Q18: =IF(I18="","",L18*IF(J18="",$B$8,J18)) | R18: =IF(I18="","",N18+O18+P18+Q18) | S18: =IF(I18="","",IF($B$6="Ja",0,R18*0.19)) | T18: =IF(I18="","",L18-L18/(1+$B$5)) | U18: =IF(I18="","",D18+E18+F18+G18) | V18: =IF(I18="","",U18*K18) | W18: =IF(I18="","",L18-R18-S18-T18-U18-V18) | X18: =IF(I18="","",IF(L18=0,0,W18/L18)) | Y18: =IF(I18="","",IF(D18=0,0,W18/D18)) | Z18: =IF(I18="","",IF(1-((M18+IF(J18="",$B$8,J18))*(1+IF($B$6="Ja",0,0.19))+$B$5/(1+$B$5))<=0,"n/a",((O18+P18)*(1+IF($B$6="Ja",0,0.19))+U18+V18)/(1-((M18+IF(J18="",$B$8,J18))*(1+IF($B$6="Ja",0,0.19))+$B$5/(1+$B$5)))-H18)) | AA18: =IF(I18="","",IF(1-((M18+IF(J18="",$B$8,J18))*(1+IF($B$6="Ja",0,0.19))+$B$5/(1+$B$5))-$B$7<=0,"n/a",((O18+P18)*(1+IF($B$6="Ja",0,0.19))+U18+V18)/(1-((M18+IF(J18="",$B$8,J18))*(1+IF($B$6="Ja",0,0.19))+$B$5/(1+$B$5))-$B$7)-H18)) | AB18: =IF(I18="","",IF(W18<0,"Verlust",IF(X18<$B$7,"unter Wunschmarge","ok")))
A19: 7 | L19: =IF(I19="","",I19+H19) | M19: =IF(I19="","",IF($B$4="Privat",0,IFERROR(INDEX(Gebühren!$B$2:$B$18,MATCH(C19,Gebühren!$A$2:$A$18,0)),0.14))) | N19: =IF(I19="","",IF($B$4="Privat",0,IF(OR(IFERROR(INDEX(Gebühren!$C$2:$C$18,MATCH(C19,Gebühren!$A$2:$A$18,0)),0)=0,L19<=IFERROR(INDEX(Gebühren!$C$2:$C$18,MATCH(C19,Gebühren!$A$2:$A$18,0)),0)),L19*M19,INDEX(Gebühren!$C$2:$C$18,MATCH(C19,Gebühren!$A$2:$A$18,0))*M19+(L19-INDEX(Gebühren!$C$2:$C$18,MATCH(C19,Gebühren!$A$2:$A$18,0)))*IFERROR(INDEX(Gebühren!$D$2:$D$18,MATCH(C19,Gebühren!$A$2:$A$18,0)),0.03)))) | O19: =IF(I19="","",IF($B$4="Privat",0,IF(L19<=10,Gebühren!$B$21,Gebühren!$B$22))) | P19: =IF(I19="","",IF($B$4="Privat",0,Gebühren!$B$23/MAX(1,$B$9))) | Q19: =IF(I19="","",L19*IF(J19="",$B$8,J19)) | R19: =IF(I19="","",N19+O19+P19+Q19) | S19: =IF(I19="","",IF($B$6="Ja",0,R19*0.19)) | T19: =IF(I19="","",L19-L19/(1+$B$5)) | U19: =IF(I19="","",D19+E19+F19+G19) | V19: =IF(I19="","",U19*K19) | W19: =IF(I19="","",L19-R19-S19-T19-U19-V19) | X19: =IF(I19="","",IF(L19=0,0,W19/L19)) | Y19: =IF(I19="","",IF(D19=0,0,W19/D19)) | Z19: =IF(I19="","",IF(1-((M19+IF(J19="",$B$8,J19))*(1+IF($B$6="Ja",0,0.19))+$B$5/(1+$B$5))<=0,"n/a",((O19+P19)*(1+IF($B$6="Ja",0,0.19))+U19+V19)/(1-((M19+IF(J19="",$B$8,J19))*(1+IF($B$6="Ja",0,0.19))+$B$5/(1+$B$5)))-H19)) | AA19: =IF(I19="","",IF(1-((M19+IF(J19="",$B$8,J19))*(1+IF($B$6="Ja",0,0.19))+$B$5/(1+$B$5))-$B$7<=0,"n/a",((O19+P19)*(1+IF($B$6="Ja",0,0.19))+U19+V19)/(1-((M19+IF(J19="",$B$8,J19))*(1+IF($B$6="Ja",0,0.19))+$B$5/(1+$B$5))-$B$7)-H19)) | AB19: =IF(I19="","",IF(W19<0,"Verlust",IF(X19<$B$7,"unter Wunschmarge","ok")))
A20: 8 | L20: =IF(I20="","",I20+H20) | M20: =IF(I20="","",IF($B$4="Privat",0,IFERROR(INDEX(Gebühren!$B$2:$B$18,MATCH(C20,Gebühren!$A$2:$A$18,0)),0.14))) | N20: =IF(I20="","",IF($B$4="Privat",0,IF(OR(IFERROR(INDEX(Gebühren!$C$2:$C$18,MATCH(C20,Gebühren!$A$2:$A$18,0)),0)=0,L20<=IFERROR(INDEX(Gebühren!$C$2:$C$18,MATCH(C20,Gebühren!$A$2:$A$18,0)),0)),L20*M20,INDEX(Gebühren!$C$2:$C$18,MATCH(C20,Gebühren!$A$2:$A$18,0))*M20+(L20-INDEX(Gebühren!$C$2:$C$18,MATCH(C20,Gebühren!$A$2:$A$18,0)))*IFERROR(INDEX(Gebühren!$D$2:$D$18,MATCH(C20,Gebühren!$A$2:$A$18,0)),0.03)))) | O20: =IF(I20="","",IF($B$4="Privat",0,IF(L20<=10,Gebühren!$B$21,Gebühren!$B$22))) | P20: =IF(I20="","",IF($B$4="Privat",0,Gebühren!$B$23/MAX(1,$B$9))) | Q20: =IF(I20="","",L20*IF(J20="",$B$8,J20)) | R20: =IF(I20="","",N20+O20+P20+Q20) | S20: =IF(I20="","",IF($B$6="Ja",0,R20*0.19)) | T20: =IF(I20="","",L20-L20/(1+$B$5)) | U20: =IF(I20="","",D20+E20+F20+G20) | V20: =IF(I20="","",U20*K20) | W20: =IF(I20="","",L20-R20-S20-T20-U20-V20) | X20: =IF(I20="","",IF(L20=0,0,W20/L20)) | Y20: =IF(I20="","",IF(D20=0,0,W20/D20)) | Z20: =IF(I20="","",IF(1-((M20+IF(J20="",$B$8,J20))*(1+IF($B$6="Ja",0,0.19))+$B$5/(1+$B$5))<=0,"n/a",((O20+P20)*(1+IF($B$6="Ja",0,0.19))+U20+V20)/(1-((M20+IF(J20="",$B$8,J20))*(1+IF($B$6="Ja",0,0.19))+$B$5/(1+$B$5)))-H20)) | AA20: =IF(I20="","",IF(1-((M20+IF(J20="",$B$8,J20))*(1+IF($B$6="Ja",0,0.19))+$B$5/(1+$B$5))-$B$7<=0,"n/a",((O20+P20)*(1+IF($B$6="Ja",0,0.19))+U20+V20)/(1-((M20+IF(J20="",$B$8,J20))*(1+IF($B$6="Ja",0,0.19))+$B$5/(1+$B$5))-$B$7)-H20)) | AB20: =IF(I20="","",IF(W20<0,"Verlust",IF(X20<$B$7,"unter Wunschmarge","ok")))
A21: 9 | L21: =IF(I21="","",I21+H21) | M21: =IF(I21="","",IF($B$4="Privat",0,IFERROR(INDEX(Gebühren!$B$2:$B$18,MATCH(C21,Gebühren!$A$2:$A$18,0)),0.14))) | N21: =IF(I21="","",IF($B$4="Privat",0,IF(OR(IFERROR(INDEX(Gebühren!$C$2:$C$18,MATCH(C21,Gebühren!$A$2:$A$18,0)),0)=0,L21<=IFERROR(INDEX(Gebühren!$C$2:$C$18,MATCH(C21,Gebühren!$A$2:$A$18,0)),0)),L21*M21,INDEX(Gebühren!$C$2:$C$18,MATCH(C21,Gebühren!$A$2:$A$18,0))*M21+(L21-INDEX(Gebühren!$C$2:$C$18,MATCH(C21,Gebühren!$A$2:$A$18,0)))*IFERROR(INDEX(Gebühren!$D$2:$D$18,MATCH(C21,Gebühren!$A$2:$A$18,0)),0.03)))) | O21: =IF(I21="","",IF($B$4="Privat",0,IF(L21<=10,Gebühren!$B$21,Gebühren!$B$22))) | P21: =IF(I21="","",IF($B$4="Privat",0,Gebühren!$B$23/MAX(1,$B$9))) | Q21: =IF(I21="","",L21*IF(J21="",$B$8,J21)) | R21: =IF(I21="","",N21+O21+P21+Q21) | S21: =IF(I21="","",IF($B$6="Ja",0,R21*0.19)) | T21: =IF(I21="","",L21-L21/(1+$B$5)) | U21: =IF(I21="","",D21+E21+F21+G21) | V21: =IF(I21="","",U21*K21) | W21: =IF(I21="","",L21-R21-S21-T21-U21-V21) | X21: =IF(I21="","",IF(L21=0,0,W21/L21)) | Y21: =IF(I21="","",IF(D21=0,0,W21/D21)) | Z21: =IF(I21="","",IF(1-((M21+IF(J21="",$B$8,J21))*(1+IF($B$6="Ja",0,0.19))+$B$5/(1+$B$5))<=0,"n/a",((O21+P21)*(1+IF($B$6="Ja",0,0.19))+U21+V21)/(1-((M21+IF(J21="",$B$8,J21))*(1+IF($B$6="Ja",0,0.19))+$B$5/(1+$B$5)))-H21)) | AA21: =IF(I21="","",IF(1-((M21+IF(J21="",$B$8,J21))*(1+IF($B$6="Ja",0,0.19))+$B$5/(1+$B$5))-$B$7<=0,"n/a",((O21+P21)*(1+IF($B$6="Ja",0,0.19))+U21+V21)/(1-((M21+IF(J21="",$B$8,J21))*(1+IF($B$6="Ja",0,0.19))+$B$5/(1+$B$5))-$B$7)-H21)) | AB21: =IF(I21="","",IF(W21<0,"Verlust",IF(X21<$B$7,"unter Wunschmarge","ok")))
A22: 10 | L22: =IF(I22="","",I22+H22) | M22: =IF(I22="","",IF($B$4="Privat",0,IFERROR(INDEX(Gebühren!$B$2:$B$18,MATCH(C22,Gebühren!$A$2:$A$18,0)),0.14))) | N22: =IF(I22="","",IF($B$4="Privat",0,IF(OR(IFERROR(INDEX(Gebühren!$C$2:$C$18,MATCH(C22,Gebühren!$A$2:$A$18,0)),0)=0,L22<=IFERROR(INDEX(Gebühren!$C$2:$C$18,MATCH(C22,Gebühren!$A$2:$A$18,0)),0)),L22*M22,INDEX(Gebühren!$C$2:$C$18,MATCH(C22,Gebühren!$A$2:$A$18,0))*M22+(L22-INDEX(Gebühren!$C$2:$C$18,MATCH(C22,Gebühren!$A$2:$A$18,0)))*IFERROR(INDEX(Gebühren!$D$2:$D$18,MATCH(C22,Gebühren!$A$2:$A$18,0)),0.03)))) | O22: =IF(I22="","",IF($B$4="Privat",0,IF(L22<=10,Gebühren!$B$21,Gebühren!$B$22))) | P22: =IF(I22="","",IF($B$4="Privat",0,Gebühren!$B$23/MAX(1,$B$9))) | Q22: =IF(I22="","",L22*IF(J22="",$B$8,J22)) | R22: =IF(I22="","",N22+O22+P22+Q22) | S22: =IF(I22="","",IF($B$6="Ja",0,R22*0.19)) | T22: =IF(I22="","",L22-L22/(1+$B$5)) | U22: =IF(I22="","",D22+E22+F22+G22) | V22: =IF(I22="","",U22*K22) | W22: =IF(I22="","",L22-R22-S22-T22-U22-V22) | X22: =IF(I22="","",IF(L22=0,0,W22/L22)) | Y22: =IF(I22="","",IF(D22=0,0,W22/D22)) | Z22: =IF(I22="","",IF(1-((M22+IF(J22="",$B$8,J22))*(1+IF($B$6="Ja",0,0.19))+$B$5/(1+$B$5))<=0,"n/a",((O22+P22)*(1+IF($B$6="Ja",0,0.19))+U22+V22)/(1-((M22+IF(J22="",$B$8,J22))*(1+IF($B$6="Ja",0,0.19))+$B$5/(1+$B$5)))-H22)) | AA22: =IF(I22="","",IF(1-((M22+IF(J22="",$B$8,J22))*(1+IF($B$6="Ja",0,0.19))+$B$5/(1+$B$5))-$B$7<=0,"n/a",((O22+P22)*(1+IF($B$6="Ja",0,0.19))+U22+V22)/(1-((M22+IF(J22="",$B$8,J22))*(1+IF($B$6="Ja",0,0.19))+$B$5/(1+$B$5))-$B$7)-H22)) | AB22: =IF(I22="","",IF(W22<0,"Verlust",IF(X22<$B$7,"unter Wunschmarge","ok")))
A23: 11 | L23: =IF(I23="","",I23+H23) | M23: =IF(I23="","",IF($B$4="Privat",0,IFERROR(INDEX(Gebühren!$B$2:$B$18,MATCH(C23,Gebühren!$A$2:$A$18,0)),0.14))) | N23: =IF(I23="","",IF($B$4="Privat",0,IF(OR(IFERROR(INDEX(Gebühren!$C$2:$C$18,MATCH(C23,Gebühren!$A$2:$A$18,0)),0)=0,L23<=IFERROR(INDEX(Gebühren!$C$2:$C$18,MATCH(C23,Gebühren!$A$2:$A$18,0)),0)),L23*M23,INDEX(Gebühren!$C$2:$C$18,MATCH(C23,Gebühren!$A$2:$A$18,0))*M23+(L23-INDEX(Gebühren!$C$2:$C$18,MATCH(C23,Gebühren!$A$2:$A$18,0)))*IFERROR(INDEX(Gebühren!$D$2:$D$18,MATCH(C23,Gebühren!$A$2:$A$18,0)),0.03)))) | O23: =IF(I23="","",IF($B$4="Privat",0,IF(L23<=10,Gebühren!$B$21,Gebühren!$B$22))) | P23: =IF(I23="","",IF($B$4="Privat",0,Gebühren!$B$23/MAX(1,$B$9))) | Q23: =IF(I23="","",L23*IF(J23="",$B$8,J23)) | R23: =IF(I23="","",N23+O23+P23+Q23) | S23: =IF(I23="","",IF($B$6="Ja",0,R23*0.19)) | T23: =IF(I23="","",L23-L23/(1+$B$5)) | U23: =IF(I23="","",D23+E23+F23+G23) | V23: =IF(I23="","",U23*K23) | W23: =IF(I23="","",L23-R23-S23-T23-U23-V23) | X23: =IF(I23="","",IF(L23=0,0,W23/L23)) | Y23: =IF(I23="","",IF(D23=0,0,W23/D23)) | Z23: =IF(I23="","",IF(1-((M23+IF(J23="",$B$8,J23))*(1+IF($B$6="Ja",0,0.19))+$B$5/(1+$B$5))<=0,"n/a",((O23+P23)*(1+IF($B$6="Ja",0,0.19))+U23+V23)/(1-((M23+IF(J23="",$B$8,J23))*(1+IF($B$6="Ja",0,0.19))+$B$5/(1+$B$5)))-H23)) | AA23: =IF(I23="","",IF(1-((M23+IF(J23="",$B$8,J23))*(1+IF($B$6="Ja",0,0.19))+$B$5/(1+$B$5))-$B$7<=0,"n/a",((O23+P23)*(1+IF($B$6="Ja",0,0.19))+U23+V23)/(1-((M23+IF(J23="",$B$8,J23))*(1+IF($B$6="Ja",0,0.19))+$B$5/(1+$B$5))-$B$7)-H23)) | AB23: =IF(I23="","",IF(W23<0,"Verlust",IF(X23<$B$7,"unter Wunschmarge","ok")))
A24: 12 | L24: =IF(I24="","",I24+H24) | M24: =IF(I24="","",IF($B$4="Privat",0,IFERROR(INDEX(Gebühren!$B$2:$B$18,MATCH(C24,Gebühren!$A$2:$A$18,0)),0.14))) | N24: =IF(I24="","",IF($B$4="Privat",0,IF(OR(IFERROR(INDEX(Gebühren!$C$2:$C$18,MATCH(C24,Gebühren!$A$2:$A$18,0)),0)=0,L24<=IFERROR(INDEX(Gebühren!$C$2:$C$18,MATCH(C24,Gebühren!$A$2:$A$18,0)),0)),L24*M24,INDEX(Gebühren!$C$2:$C$18,MATCH(C24,Gebühren!$A$2:$A$18,0))*M24+(L24-INDEX(Gebühren!$C$2:$C$18,MATCH(C24,Gebühren!$A$2:$A$18,0)))*IFERROR(INDEX(Gebühren!$D$2:$D$18,MATCH(C24,Gebühren!$A$2:$A$18,0)),0.03)))) | O24: =IF(I24="","",IF($B$4="Privat",0,IF(L24<=10,Gebühren!$B$21,Gebühren!$B$22))) | P24: =IF(I24="","",IF($B$4="Privat",0,Gebühren!$B$23/MAX(1,$B$9))) | Q24: =IF(I24="","",L24*IF(J24="",$B$8,J24)) | R24: =IF(I24="","",N24+O24+P24+Q24) | S24: =IF(I24="","",IF($B$6="Ja",0,R24*0.19)) | T24: =IF(I24="","",L24-L24/(1+$B$5)) | U24: =IF(I24="","",D24+E24+F24+G24) | V24: =IF(I24="","",U24*K24) | W24: =IF(I24="","",L24-R24-S24-T24-U24-V24) | X24: =IF(I24="","",IF(L24=0,0,W24/L24)) | Y24: =IF(I24="","",IF(D24=0,0,W24/D24)) | Z24: =IF(I24="","",IF(1-((M24+IF(J24="",$B$8,J24))*(1+IF($B$6="Ja",0,0.19))+$B$5/(1+$B$5))<=0,"n/a",((O24+P24)*(1+IF($B$6="Ja",0,0.19))+U24+V24)/(1-((M24+IF(J24="",$B$8,J24))*(1+IF($B$6="Ja",0,0.19))+$B$5/(1+$B$5)))-H24)) | AA24: =IF(I24="","",IF(1-((M24+IF(J24="",$B$8,J24))*(1+IF($B$6="Ja",0,0.19))+$B$5/(1+$B$5))-$B$7<=0,"n/a",((O24+P24)*(1+IF($B$6="Ja",0,0.19))+U24+V24)/(1-((M24+IF(J24="",$B$8,J24))*(1+IF($B$6="Ja",0,0.19))+$B$5/(1+$B$5))-$B$7)-H24)) | AB24: =IF(I24="","",IF(W24<0,"Verlust",IF(X24<$B$7,"unter Wunschmarge","ok")))
A25: 13 | L25: =IF(I25="","",I25+H25) | M25: =IF(I25="","",IF($B$4="Privat",0,IFERROR(INDEX(Gebühren!$B$2:$B$18,MATCH(C25,Gebühren!$A$2:$A$18,0)),0.14))) | N25: =IF(I25="","",IF($B$4="Privat",0,IF(OR(IFERROR(INDEX(Gebühren!$C$2:$C$18,MATCH(C25,Gebühren!$A$2:$A$18,0)),0)=0,L25<=IFERROR(INDEX(Gebühren!$C$2:$C$18,MATCH(C25,Gebühren!$A$2:$A$18,0)),0)),L25*M25,INDEX(Gebühren!$C$2:$C$18,MATCH(C25,Gebühren!$A$2:$A$18,0))*M25+(L25-INDEX(Gebühren!$C$2:$C$18,MATCH(C25,Gebühren!$A$2:$A$18,0)))*IFERROR(INDEX(Gebühren!$D$2:$D$18,MATCH(C25,Gebühren!$A$2:$A$18,0)),0.03)))) | O25: =IF(I25="","",IF($B$4="Privat",0,IF(L25<=10,Gebühren!$B$21,Gebühren!$B$22))) | P25: =IF(I25="","",IF($B$4="Privat",0,Gebühren!$B$23/MAX(1,$B$9))) | Q25: =IF(I25="","",L25*IF(J25="",$B$8,J25)) | R25: =IF(I25="","",N25+O25+P25+Q25) | S25: =IF(I25="","",IF($B$6="Ja",0,R25*0.19)) | T25: =IF(I25="","",L25-L25/(1+$B$5)) | U25: =IF(I25="","",D25+E25+F25+G25) | V25: =IF(I25="","",U25*K25) | W25: =IF(I25="","",L25-R25-S25-T25-U25-V25) | X25: =IF(I25="","",IF(L25=0,0,W25/L25)) | Y25: =IF(I25="","",IF(D25=0,0,W25/D25)) | Z25: =IF(I25="","",IF(1-((M25+IF(J25="",$B$8,J25))*(1+IF($B$6="Ja",0,0.19))+$B$5/(1+$B$5))<=0,"n/a",((O25+P25)*(1+IF($B$6="Ja",0,0.19))+U25+V25)/(1-((M25+IF(J25="",$B$8,J25))*(1+IF($B$6="Ja",0,0.19))+$B$5/(1+$B$5)))-H25)) | AA25: =IF(I25="","",IF(1-((M25+IF(J25="",$B$8,J25))*(1+IF($B$6="Ja",0,0.19))+$B$5/(1+$B$5))-$B$7<=0,"n/a",((O25+P25)*(1+IF($B$6="Ja",0,0.19))+U25+V25)/(1-((M25+IF(J25="",$B$8,J25))*(1+IF($B$6="Ja",0,0.19))+$B$5/(1+$B$5))-$B$7)-H25)) | AB25: =IF(I25="","",IF(W25<0,"Verlust",IF(X25<$B$7,"unter Wunschmarge","ok")))
A26: 14 | L26: =IF(I26="","",I26+H26) | M26: =IF(I26="","",IF($B$4="Privat",0,IFERROR(INDEX(Gebühren!$B$2:$B$18,MATCH(C26,Gebühren!$A$2:$A$18,0)),0.14))) | N26: =IF(I26="","",IF($B$4="Privat",0,IF(OR(IFERROR(INDEX(Gebühren!$C$2:$C$18,MATCH(C26,Gebühren!$A$2:$A$18,0)),0)=0,L26<=IFERROR(INDEX(Gebühren!$C$2:$C$18,MATCH(C26,Gebühren!$A$2:$A$18,0)),0)),L26*M26,INDEX(Gebühren!$C$2:$C$18,MATCH(C26,Gebühren!$A$2:$A$18,0))*M26+(L26-INDEX(Gebühren!$C$2:$C$18,MATCH(C26,Gebühren!$A$2:$A$18,0)))*IFERROR(INDEX(Gebühren!$D$2:$D$18,MATCH(C26,Gebühren!$A$2:$A$18,0)),0.03)))) | O26: =IF(I26="","",IF($B$4="Privat",0,IF(L26<=10,Gebühren!$B$21,Gebühren!$B$22))) | P26: =IF(I26="","",IF($B$4="Privat",0,Gebühren!$B$23/MAX(1,$B$9))) | Q26: =IF(I26="","",L26*IF(J26="",$B$8,J26)) | R26: =IF(I26="","",N26+O26+P26+Q26) | S26: =IF(I26="","",IF($B$6="Ja",0,R26*0.19)) | T26: =IF(I26="","",L26-L26/(1+$B$5)) | U26: =IF(I26="","",D26+E26+F26+G26) | V26: =IF(I26="","",U26*K26) | W26: =IF(I26="","",L26-R26-S26-T26-U26-V26) | X26: =IF(I26="","",IF(L26=0,0,W26/L26)) | Y26: =IF(I26="","",IF(D26=0,0,W26/D26)) | Z26: =IF(I26="","",IF(1-((M26+IF(J26="",$B$8,J26))*(1+IF($B$6="Ja",0,0.19))+$B$5/(1+$B$5))<=0,"n/a",((O26+P26)*(1+IF($B$6="Ja",0,0.19))+U26+V26)/(1-((M26+IF(J26="",$B$8,J26))*(1+IF($B$6="Ja",0,0.19))+$B$5/(1+$B$5)))-H26)) | AA26: =IF(I26="","",IF(1-((M26+IF(J26="",$B$8,J26))*(1+IF($B$6="Ja",0,0.19))+$B$5/(1+$B$5))-$B$7<=0,"n/a",((O26+P26)*(1+IF($B$6="Ja",0,0.19))+U26+V26)/(1-((M26+IF(J26="",$B$8,J26))*(1+IF($B$6="Ja",0,0.19))+$B$5/(1+$B$5))-$B$7)-H26)) | AB26: =IF(I26="","",IF(W26<0,"Verlust",IF(X26<$B$7,"unter Wunschmarge","ok")))
A27: 15 | L27: =IF(I27="","",I27+H27) | M27: =IF(I27="","",IF($B$4="Privat",0,IFERROR(INDEX(Gebühren!$B$2:$B$18,MATCH(C27,Gebühren!$A$2:$A$18,0)),0.14))) | N27: =IF(I27="","",IF($B$4="Privat",0,IF(OR(IFERROR(INDEX(Gebühren!$C$2:$C$18,MATCH(C27,Gebühren!$A$2:$A$18,0)),0)=0,L27<=IFERROR(INDEX(Gebühren!$C$2:$C$18,MATCH(C27,Gebühren!$A$2:$A$18,0)),0)),L27*M27,INDEX(Gebühren!$C$2:$C$18,MATCH(C27,Gebühren!$A$2:$A$18,0))*M27+(L27-INDEX(Gebühren!$C$2:$C$18,MATCH(C27,Gebühren!$A$2:$A$18,0)))*IFERROR(INDEX(Gebühren!$D$2:$D$18,MATCH(C27,Gebühren!$A$2:$A$18,0)),0.03)))) | O27: =IF(I27="","",IF($B$4="Privat",0,IF(L27<=10,Gebühren!$B$21,Gebühren!$B$22))) | P27: =IF(I27="","",IF($B$4="Privat",0,Gebühren!$B$23/MAX(1,$B$9))) | Q27: =IF(I27="","",L27*IF(J27="",$B$8,J27)) | R27: =IF(I27="","",N27+O27+P27+Q27) | S27: =IF(I27="","",IF($B$6="Ja",0,R27*0.19)) | T27: =IF(I27="","",L27-L27/(1+$B$5)) | U27: =IF(I27="","",D27+E27+F27+G27) | V27: =IF(I27="","",U27*K27) | W27: =IF(I27="","",L27-R27-S27-T27-U27-V27) | X27: =IF(I27="","",IF(L27=0,0,W27/L27)) | Y27: =IF(I27="","",IF(D27=0,0,W27/D27)) | Z27: =IF(I27="","",IF(1-((M27+IF(J27="",$B$8,J27))*(1+IF($B$6="Ja",0,0.19))+$B$5/(1+$B$5))<=0,"n/a",((O27+P27)*(1+IF($B$6="Ja",0,0.19))+U27+V27)/(1-((M27+IF(J27="",$B$8,J27))*(1+IF($B$6="Ja",0,0.19))+$B$5/(1+$B$5)))-H27)) | AA27: =IF(I27="","",IF(1-((M27+IF(J27="",$B$8,J27))*(1+IF($B$6="Ja",0,0.19))+$B$5/(1+$B$5))-$B$7<=0,"n/a",((O27+P27)*(1+IF($B$6="Ja",0,0.19))+U27+V27)/(1-((M27+IF(J27="",$B$8,J27))*(1+IF($B$6="Ja",0,0.19))+$B$5/(1+$B$5))-$B$7)-H27)) | AB27: =IF(I27="","",IF(W27<0,"Verlust",IF(X27<$B$7,"unter Wunschmarge","ok")))
... A72: 60 | L72: =IF(I72="","",I72+H72) | M72: =IF(I72="","",IF($B$4="Privat",0,IFERROR(INDEX(Gebühren!$B$2:$B$18,MATCH(C72,Gebühren!$A$2:$A$18,0)),0.14))) | N72: =IF(I72="","",IF($B$4="Privat",0,IF(OR(IFERROR(INDEX(Gebühren!$C$2:$C$18,MATCH(C72,Gebühren!$A$2:$A$18,0)),0)=0,L72<=IFERROR(INDEX(Gebühren!$C$2:$C$18,MATCH(C72,Gebühren!$A$2:$A$18,0)),0)),L72*M72,INDEX(Gebühren!$C$2:$C$18,MATCH(C72,Gebühren!$A$2:$A$18,0))*M72+(L72-INDEX(Gebühren!$C$2:$C$18,MATCH(C72,Gebühren!$A$2:$A$18,0)))*IFERROR(INDEX(Gebühren!$D$2:$D$18,MATCH(C72,Gebühren!$A$2:$A$18,0)),0.03)))) | O72: =IF(I72="","",IF($B$4="Privat",0,IF(L72<=10,Gebühren!$B$21,Gebühren!$B$22))) | P72: =IF(I72="","",IF($B$4="Privat",0,Gebühren!$B$23/MAX(1,$B$9))) | Q72: =IF(I72="","",L72*IF(J72="",$B$8,J72)) | R72: =IF(I72="","",N72+O72+P72+Q72) | S72: =IF(I72="","",IF($B$6="Ja",0,R72*0.19)) | T72: =IF(I72="","",L72-L72/(1+$B$5)) | U72: =IF(I72="","",D72+E72+F72+G72) | V72: =IF(I72="","",U72*K72) | W72: =IF(I72="","",L72-R72-S72-T72-U72-V72) | X72: =IF(I72="","",IF(L72=0,0,W72/L72)) | Y72: =IF(I72="","",IF(D72=0,0,W72/D72)) | Z72: =IF(I72="","",IF(1-((M72+IF(J72="",$B$8,J72))*(1+IF($B$6="Ja",0,0.19))+$B$5/(1+$B$5))<=0,"n/a",((O72+P72)*(1+IF($B$6="Ja",0,0.19))+U72+V72)/(1-((M72+IF(J72="",$B$8,J72))*(1+IF($B$6="Ja",0,0.19))+$B$5/(1+$B$5)))-H72)) | AA72: =IF(I72="","",IF(1-((M72+IF(J72="",$B$8,J72))*(1+IF($B$6="Ja",0,0.19))+$B$5/(1+$B$5))-$B$7<=0,"n/a",((O72+P72)*(1+IF($B$6="Ja",0,0.19))+U72+V72)/(1-((M72+IF(J72="",$B$8,J72))*(1+IF($B$6="Ja",0,0.19))+$B$5/(1+$B$5))-$B$7)-H72)) | AB72: =IF(I72="","",IF(W72<0,"Verlust",IF(X72<$B$7,"unter Wunschmarge","ok")))
B74: Summe / Durchschnitt | L74: =SUM(L13:L72) -> 59.96 | R74: =SUM(R13:R72) -> 10.0948 | W74: =SUM(W13:W72) -> 9.1047546 | X74: =IF(L74=0,0,W74/L74) -> 0.15184714
B75: Beispielzeilen 1 bis 3 sind erfundene Werte zum Zeigen des Formats, einfach überschreiben.

Sheet Gebühren
A1: Kategorie-Gruppe | B1: Provision gewerblich | C1: Staffel-Schwelle (€) | D1: Satz über Schwelle | E1: Hinweis
A2: Technik: Geräte (Computer, Handys, Konsolen, TV, Haushaltsgeräte, Foto) | B2: 0.07 | E2: Neuware. Gebraucht/Refurbished teils 5 %.
A3: Technik: Zubehör (Kabel, Handy-Zubehör, Hüllen, Tastaturen, Ladegeräte) | B3: 0.12 | E3: Typische Temu-Artikel landen oft hier.
A4: Haus & Garten: Garten & Terrasse, Heimwerker | B4: 0.13
A5: Möbel & Wohnen (Deko, Küche, Organizer, Haushalt ohne Elektrogeräte) | B5: 0.14
A6: Sport, Baby, Bastelbedarf, Haustierbedarf, Feinschmecker, Reisen, Verschiedenes | B6: 0.14
A7: Business & Industrie, Büro & Schreibwaren | B7: 0.14
A8: Musikinstrumente | B8: 0.11
A9: Kleidung & Accessoires | B9: 0.12 | C9: 990 | D9: 0.03 | E9: 12 % bis 990 €, darüber 3 %.
A10: Sneaker unter 100 € | B10: 0.12 | C10: 990 | D10: 0.03 | E10: Ab 100 € Verkaufspreis nur 7 %.
A11: Uhren & Schmuck (ohne Shop) | B11: 0.16 | C11: 990 | D11: 0.03 | E11: Teilkategorien wie Armbanduhren 11 %.
A12: Medien: Bücher, Filme, Musik, Spiele | B12: 0.12 | C12: 990 | D12: 0.03
A13: Auto & Motorrad: Teile | B13: 0.12 | C13: 990 | D13: 0.03
A14: Modellbau | B14: 0.11 | C14: 990 | D14: 0.03
A15: Antiquitäten & Kunst | B15: 0.12 | C15: 990 | D15: 0.03
A16: Münzen | B16: 0.065 | C16: 990 | D16: 0.03
A17: Spielzeug / Beauty & Gesundheit / Sammeln (Satz auf eBay-Seite prüfen) | B17: 0.14 | E17: Auf der eBay-Seite nicht eindeutig lesbar, konservativ 14 % angesetzt. Bitte prüfen.
A18: Unbekannt / konservativ | B18: 0.14 | E18: Höchster Standardsatz als Sicherheitsannahme.
A20: Weitere Gebühren (gewerblich, ohne Shop)
A21: Fixanteil je Bestellung bis 10,00 € Gesamtbetrag | B21: 0.35
A22: Fixanteil je Bestellung über 10,00 € Gesamtbetrag | B22: 0.45
A23: Angebotsgebühr je Festpreisangebot und Monat (ohne Shop) | B23: 0.35
A24: Angebotsgebühr je Auktion (ohne Shop) | B24: 0.5
A25: Shop Basis: 39,95 €/Monat, 400 Festpreisangebote frei, danach 0,10 €
A26: Internationale Gebühr außerhalb Eurozone/Schweden ohne eBay Internationalen Versand: 1,2 % bis 3,3 %
A27: Alle Sätze netto, zzgl. 19 % USt auf die eBay-Rechnung
A29: Private Verkäufer (eBay.de, Inland)
A30: Provision und Fixanteil | B30: 0 € (seit 1. März 2023 kostenlos)
A31: Kostenlose Angebote pro Monat | B31: 320, danach 0,50 € je Angebot
A32: Selbst organisierter Versand ins Ausland | B32: 5 % des Gesamtbetrags
A33: Wichtig | B33: Regelmäßiger Handel mit Neuware ist kein Privatverkauf. eBay stuft solche Konten um, das Finanzamt bekommt Daten über die Plattformen-Meldepflicht (DAC7).
A35: Quelle: https://www.ebay.de/help/selling/fees-credits-invoices/gebhren-fr-gewerbliche-verkufer?id=4809 und https://www.ebay.de/help/selling/fees-credits-invoices/selling-fees?id=4822, abgerufen am 19.10.2026. Prozentsätze in Spalte B sind Eingaben und können bei Gebührenänderungen angepasst werden.

Sheet Upload-Vorlage
A1: Action(SiteID=Germany|Country=DE|Currency=EUR|Version=1193) | B1: Custom label (SKU) | C1: Category ID | D1: Title | E1: Subtitle | F1: Relationship | G1: Relationship details | H1: Schedule Time | I1: P:EAN | J1: P:UPC | K1: P:EPID | L1: Start price | M1: Quantity | N1: Item photo URL | O1: VideoID | P1: Condition ID | Q1: Description | R1: Format | S1: Duration | T1: Buy It Now price | U1: Best Offer Enabled | V1: Best Offer Auto Accept Price | W1: Minimum Best Offer Price | X1: VAT% | Y1: Location | Z1: PostalCode | AA1: Shipping profile name | AB1: Return profile name | AC1: Payment profile name | AD1: Shipping service 1 option | AE1: Shipping service 1 cost | AF1: Shipping service 1 priority | AG1: Shipping service 2 option | AH1: Shipping service 2 cost | AI1: Shipping service 2 priority | AJ1: Max dispatch time | AK1: Returns accepted option | AL1: Returns within option | AM1: Refund option | AN1: Return shipping cost paid by | AO1: ProductCompliancePolicyID | AP1: Regional ProductCompliancePolicies | AQ1: C:Marke | AR1: C:Herstellernummer | AS1: C:Farbe | AT1: C:Material | AU1: C:Herstellungsland und -region
A2: Add = neu einstellen, Revise = ändern, End = beenden, VerifyAdd = nur prüfen. Kopfzeile NICHT ändern; mit der von eBay heruntergeladenen Vorlage abgleichen (Version kann abweichen). | B2: Deine Artikelnummer, frei wählbar, Käufer sieht sie nicht. Am besten gleich wie Spalte 'Artikel / SKU' in der Kalkulation. | C2: Numerische eBay-Kategorie-ID. Im Verkäufer-Cockpit beim manuellen Einstellen ablesen oder Kategorie-Suche nutzen. | D2: Max. 80 Zeichen. Suchbegriffe nach vorn: Produktart, Marke/Typ, Menge, Größe, Farbe. | E2: Untertitel, kostet 1,50 € (gewerblich) bzw. 0,50 € (privat). Meist leer lassen. | F2: Leer bei normalen Angeboten. 'Variation' in Kindzeilen bei Varianten (Größe/Farbe). | G2: Varianten-Definition, z. B. Farbe=Schwarz;Weiß|Größe=S;M. Leer bei normalen Angeboten. | H2: Optionaler Startzeitpunkt JJJJ-MM-TT HH:MM:SS. Leer = sofort. | I2: EAN (13 Stellen) oder 'Nicht zutreffend' wenn der Artikel keine hat (bei Temu-Ware meist der Fall). | J2: Nur für US-Artikel nötig, hier leer. | K2: eBay-Produkt-ID aus dem Katalog, optional. | L2: Verkaufspreis in EUR mit Punkt als Dezimaltrenner, z. B. 19.99. Aus Spalte 'Zielpreis' der Kalkulation. | M2: Stückzahl, ganze Zahl. Nur Ware eintragen, die du wirklich vorrätig hast. | N2: Bild-URLs mit https://, Endung .jpg oder .png, mehrere mit | trennen. Erstes Bild = Hauptbild. Nur eigene Fotos verwenden. | O2: Optional, eBay-Video-ID. | P2: 1000 = Neu, 1500 = Neu: Sonstige, 2500 = Vom Verkäufer generalüberholt, 3000 = Gebraucht. | Q2: Artikelbeschreibung, einfaches HTML erlaubt (<p>, <br>, <ul>). Gewerblich: Widerruf/Impressum laufen über die eBay-Rahmenbedingungen, trotzdem vollständige Produktangaben machen. | R2: FixedPrice oder Auction. | S2: GTC bei FixedPrice (läuft bis auf Widerruf). Bei Auction: 1, 3, 5, 7 oder 10. | T2: Nur bei Auction: Sofort-Kaufen-Preis. | U2: 1 = Preisvorschlag erlauben, 0 = nicht. | V2: Preisvorschläge ab diesem Betrag automatisch annehmen (optional). | W2: Preisvorschläge unter diesem Betrag automatisch ablehnen (optional). | X2: USt-Satz, z. B. 19. Nur bei Regelbesteuerung ausfüllen, sonst leer. | Y2: Artikelstandort, z. B. Ostfildern. | Z2: Postleitzahl des Artikelstandorts. | AA2: Name deiner Versand-Rahmenbedingung EXAKT wie im Verkäufer-Cockpit (Groß-/Kleinschreibung). Wenn du Rahmenbedingungen nutzt, Spalten 'Shipping service…' bis 'Return shipping…' leer lassen. | AB2: Name deiner Rücknahme-Rahmenbedingung, exakt. | AC2: Name deiner Zahlungs-Rahmenbedingung, exakt. | AD2: Nur ohne Rahmenbedingungen: Versandservice-Code, z. B. DE_DHLPaket, DE_DHLPaeckchen, DE_HermesPaket, DE_DeutschePostBrief. | AE2: Versandkosten für Käufer in EUR, 0.00 = kostenloser Versand. | AF2: 1 = erste Versandoption. | AG2: Zweite Versandoption, optional. | AH2: Kosten zweite Option. | AI2: 2. | AJ2: Bearbeitungszeit in Werktagen: 1, 2, 3, 4, 5, 10, 15, 20, 30. Nur möglich, wenn du die Ware selbst lagerst. | AK2: ReturnsAccepted oder ReturnsNotAccepted. Gewerblich: Rücknahme ist Pflicht (14 Tage Widerruf). | AL2: Days_14, Days_30 oder Days_60. | AM2: MoneyBack oder MoneyBackOrReplacement. | AN2: Buyer oder Seller. | AO2: ID deiner Produktsicherheits-Rahmenbedingung (GPSR: Hersteller, EU-Verantwortlicher, Warnhinweise). Pflicht für Neuware seit 13.12.2024. | AP2: Regionale Produktsicherheits-Angaben, optional. | AQ2: Artikelmerkmal Marke. 'Markenlos' wenn keine Marke. | AR2: Artikelmerkmal Herstellernummer oder 'Nicht zutreffend'. | AS2: Artikelmerkmal Farbe. | AT2: Artikelmerkmal Material. | AU2: Herstellungsland, z. B. China. Weitere Pflichtmerkmale je Kategorie als Spalte C:<Merkmalname> ergänzen.
A3: Add | B3: LED-5M-RGB-001 | C3: 20702 | D3: LED Streifen 5m RGB mit Fernbedienung selbstklebend dimmbar 16 Farben USB | I3: Nicht zutreffend | L3: 19.99 | M3: 5 | N3: https://DEINE-DOMAIN.de/bilder/led-5m-01.jpg|https://DEINE-DOMAIN.de/bilder/led-5m-02.jpg | P3: 1000 | Q3: <p>LED-Streifen 5 m, RGB, 16 Farben, dimmbar, mit Fernbedienung und USB-Anschluss.</p><p>Lieferumfang: 1x LED-Streifen 5 m, 1x Fernbedienung, 1x USB-Controller.</p><p>Versand aus Deutschland, Rechnung mit ausgewiesener USt.</p> | R3: FixedPrice | S3: GTC | U3: 0 | X3: 19 | Y3: Ostfildern | Z3: 73760 | AA3: Standardversand DHL | AB3: Rücknahme 30 Tage | AC3: eBay Zahlungen | AQ3: Markenlos | AR3: Nicht zutreffend | AS3: Mehrfarbig | AT3: Kunststoff | AU3: China
A26: Vor dem Upload: Zeile 2 (Erklärungen) löschen, Beispielzeile 3 anpassen oder löschen, dann 'Speichern unter' > CSV UTF-8. Hochladen im Verkäufer-Cockpit: Berichte > Hochladen. Ergebnisbericht prüfen, letzte Spalte zeigt Fehler je Zeile.
